graphemex-0.1.5.dist-info/METADATA
graphemex-0.1.5.dist-info/WHEEL
graphemex-0.1.5.dist-info/licenses/LICENSE
graphemex/__init__.py
graphemex/graphemex.abi3.so
graphemex-0.1.5.dist-info/RECORD
