Metadata-Version: 2.4
Name: graphemex
Version: 0.1.5
Classifier: Programming Language :: Python :: 3
Classifier: Programming Language :: Rust
Classifier: License :: OSI Approved :: MIT License
Classifier: Operating System :: OS Independent
License-File: LICENSE
Summary: Fast Unicode grapheme cluster segmentation with Rust + PyO3
Keywords: unicode,grapheme,segmentation,rust,pyo3
Author: Alexandr Sukhryn alexandrvirtual@gmail.com
Author-email: Alexandr Sukhryn <alexandrvirtual@gmail.com>
License: MIT
Requires-Python: >=3.7
